{
  "model_config": {
    "input_size": 4,
    "hidden_size": 64,
    "num_layers": 1,
    "num_classes": 2,
    "dropout": 0.2
  },
  "window_config": {
    "feature_mode": "filtered_signal",
    "window_sec": 2.0,
    "stride_sec": 0.2,
    "label_mode": "endpoint"
  },
  "training_config": {
    "train_fraction": 1.0,
    "hidden_size": 64,
    "num_layers": 1,
    "dropout": 0.2,
    "batch_size": 64,
    "epochs": 20,
    "lr": 0.001,
    "seed": 888,
    "deterministic": true,
    "device": null
  },
  "normalizer_mean": [
    [
      [
        1.1415149856475182e-06,
        9.660552677814849e-07,
        9.742758493302972e-07,
        5.478066782416136e-07
      ]
    ]
  ],
  "normalizer_std": [
    [
      [
        0.10981987416744232,
        0.10534223914146423,
        0.10123378038406372,
        0.10939037799835205
      ]
    ]
  ],
  "fs": 200,
  "class_names": [
    "Eyes Open",
    "Eyes Closed"
  ],
  "source_files": [
    "e:\\UCI\\BCI\\online\\online_bci\\online_eeg\\runs_offline_eog\\offline_eog_002_vs_003\\labeled\\run_002__run_002_train_eog_offset_labeled.npz"
  ],
  "final_val_summary": [
    {
      "n_windows": 1,
      "accuracy": 1.0,
      "balanced_accuracy": 1.0
    }
  ],
  "history": [
    {
      "epoch": 1,
      "train_loss": 0.6735385690759492,
      "train_acc": 0.5684563758389262,
      "val_loss": 0.538300633430481,
      "val_acc": 1.0
    },
    {
      "epoch": 2,
      "train_loss": 0.462656656627687,
      "train_acc": 0.8476510067114094,
      "val_loss": 0.05628576502203941,
      "val_acc": 1.0
    },
    {
      "epoch": 3,
      "train_loss": 0.2946563436480977,
      "train_acc": 0.9006711409395973,
      "val_loss": 0.036539919674396515,
      "val_acc": 1.0
    },
    {
      "epoch": 4,
      "train_loss": 0.44950979259990204,
      "train_acc": 0.8013422818791947,
      "val_loss": 0.05909128487110138,
      "val_acc": 1.0
    },
    {
      "epoch": 5,
      "train_loss": 0.7273105147700982,
      "train_acc": 0.5174496644295302,
      "val_loss": 0.29431062936782837,
      "val_acc": 1.0
    },
    {
      "epoch": 6,
      "train_loss": 0.6324632195818344,
      "train_acc": 0.5375838926174497,
      "val_loss": 0.3146248757839203,
      "val_acc": 1.0
    },
    {
      "epoch": 7,
      "train_loss": 0.5914536115307136,
      "train_acc": 0.6731543624161074,
      "val_loss": 0.21537496149539948,
      "val_acc": 1.0
    },
    {
      "epoch": 8,
      "train_loss": 0.40728077184433903,
      "train_acc": 0.8442953020134228,
      "val_loss": 0.09300116449594498,
      "val_acc": 1.0
    },
    {
      "epoch": 9,
      "train_loss": 0.283722335100174,
      "train_acc": 0.9073825503355705,
      "val_loss": 0.04165508225560188,
      "val_acc": 1.0
    },
    {
      "epoch": 10,
      "train_loss": 0.3273294654968601,
      "train_acc": 0.887248322147651,
      "val_loss": 0.034558601677417755,
      "val_acc": 1.0
    },
    {
      "epoch": 11,
      "train_loss": 0.30736036680688794,
      "train_acc": 0.8926174496644296,
      "val_loss": 0.02363123744726181,
      "val_acc": 1.0
    },
    {
      "epoch": 12,
      "train_loss": 0.2893853993623849,
      "train_acc": 0.8993288590604027,
      "val_loss": 0.02061815746128559,
      "val_acc": 1.0
    },
    {
      "epoch": 13,
      "train_loss": 0.26539695418921094,
      "train_acc": 0.9134228187919463,
      "val_loss": 0.01936740055680275,
      "val_acc": 1.0
    },
    {
      "epoch": 14,
      "train_loss": 0.28415259490877187,
      "train_acc": 0.9080536912751678,
      "val_loss": 0.022894926369190216,
      "val_acc": 1.0
    },
    {
      "epoch": 15,
      "train_loss": 0.2746081599853183,
      "train_acc": 0.9114093959731544,
      "val_loss": 0.0222959965467453,
      "val_acc": 1.0
    },
    {
      "epoch": 16,
      "train_loss": 0.32928654003463337,
      "train_acc": 0.8738255033557047,
      "val_loss": 0.03464807569980621,
      "val_acc": 1.0
    },
    {
      "epoch": 17,
      "train_loss": 0.2711384492832542,
      "train_acc": 0.9120805369127517,
      "val_loss": 0.05001699551939964,
      "val_acc": 1.0
    },
    {
      "epoch": 18,
      "train_loss": 0.25346534564191064,
      "train_acc": 0.9187919463087248,
      "val_loss": 0.030653858557343483,
      "val_acc": 1.0
    },
    {
      "epoch": 19,
      "train_loss": 0.3582645116236386,
      "train_acc": 0.8348993288590604,
      "val_loss": 0.043106332421302795,
      "val_acc": 1.0
    },
    {
      "epoch": 20,
      "train_loss": 0.2620808692186471,
      "train_acc": 0.9120805369127517,
      "val_loss": 0.0347924642264843,
      "val_acc": 1.0
    }
  ]
}